kagenda/__init__.py
kagenda/__main__.py
kagenda/agenda.py
kagenda/cal.py
kagenda/config.py
kagenda/printer.py
kagenda/speech.py
kagenda/todo.py
kagenda/wx.py
kagenda-1.3.4.data/scripts/agenda
kagenda-1.3.4.dist-info/METADATA
kagenda-1.3.4.dist-info/WHEEL
kagenda-1.3.4.dist-info/top_level.txt
kagenda-1.3.4.dist-info/RECORD
