Metadata-Version: 2.1
Name: kagenda
Version: 1.3.4
Summary: Every morning, I like to get my daily agenda.
Home-page: https://github.com/kisom/kagenda
Author: kyle
Author-email: coder@kyleisom.net
License: MIT
Platform: UNKNOWN
Requires-Dist: adafruit-circuitpython-thermal-printer
Requires-Dist: darkskylib
Requires-Dist: google-api-python-client
Requires-Dist: natural
Requires-Dist: oauth2client
Requires-Dist: py-trello
Requires-Dist: pyserial
Requires-Dist: pyttsx3
Requires-Dist: pytz
